jour/__init__.py
jour/__main__.py
jour/jour.py
jour-2.0.2.dist-info/LICENSE
jour-2.0.2.dist-info/METADATA
jour-2.0.2.dist-info/WHEEL
jour-2.0.2.dist-info/entry_points.txt
jour-2.0.2.dist-info/RECORD
