Metadata-Version: 2.1
Name: jour
Version: 2.0.2
Summary: An utility for a high-level machine maintenance journal
Home-page: https://github.com/bglezseoane/jour
License: LICENSE
Keywords: configuration,journal,journaling,machine-administration,machine-maintenance,markdown
Author: Borja González Seoane
Author-email: borja@glezseoane.es
Requires-Python: >=3.11,<4.0
Classifier: Intended Audience :: End Users/Desktop
Classifier: Intended Audience :: Information Technology
Classifier: License :: Other/Proprietary License
Classifier: Operating System :: OS Independent
Classifier: Operating System :: POSIX
Classifier: Programming Language :: Python :: 3
Classifier: Programming Language :: Python :: 3.11
Classifier: Programming Language :: Python :: 3.12
Classifier: Topic :: System :: Logging
Classifier: Topic :: Utilities
Requires-Dist: ilock (>=1.0.3,<2.0.0)
Requires-Dist: mdformat (>=0.7.17,<0.8.0)
Project-URL: Repository, https://github.com/bglezseoane/jour
